.gitignore
CHANGES.txt
LICENSE
README.rst
buildout.cfg
pytest.ini
requirements.txt
setup.py
tox.ini
src/celery_redis_sync/__init__.py
src/celery_redis_sync/conftest.py
src/celery_redis_sync/redis_sync.py
src/celery_redis_sync.egg-info/PKG-INFO
src/celery_redis_sync.egg-info/SOURCES.txt
src/celery_redis_sync.egg-info/dependency_links.txt
src/celery_redis_sync.egg-info/entry_points.txt
src/celery_redis_sync.egg-info/not-zip-safe
src/celery_redis_sync.egg-info/requires.txt
src/celery_redis_sync.egg-info/top_level.txt
src/celery_redis_sync/tests/__init__.py
src/celery_redis_sync/tests/test_redis.py