Metadata-Version: 1.0
Name: celery-redis-sync
Version: 1.0.0
Summary: Synchronous Redis result store backend
Home-page: https://github.com/zeitonline/celery_redis_sync
Author: Zeit Online
Author-email: zon-backend@zeit.de
License: BSD
Platform: UNKNOWN
